ismeowix/__init__.py
ismeowix/ismeowix.py
ismeowix-0.4.dist-info/LICENSE
ismeowix-0.4.dist-info/METADATA
ismeowix-0.4.dist-info/WHEEL
ismeowix-0.4.dist-info/top_level.txt
ismeowix-0.4.dist-info/RECORD
