Metadata-Version: 2.1
Name: ismeowix
Version: 0.4
Summary: Library for Meowix Python applications to check if the intended operating system is being used
Home-page: https://github.com/Meowix-Linux/python-ismeowix
Author: Nekosis
Project-URL: Bug Tracker, https://github.com/Meowix-Linux/python-ismeowix/issues
Classifier: Programming Language :: Python :: 3
Classifier: License :: OSI Approved :: GNU General Public License v3 (GPLv3)
Classifier: Operating System :: OS Independent
License-File: LICENSE
Requires-Dist: distro
Requires-Dist: colorama
